Metadata-Version: 1.0
Name: s3am
Version: 2.1.0a1.dev115
Summary: Efficiently transfer large amounts of data to S3
Home-page: https://github.com/BD2KGenomics/cgcloud
Author: Hannes Schmidt
Author-email: hannes@ucsc.edu
License: UNKNOWN
Platform: UNKNOWN
